README.md
setup.py
kkkit.egg-info/PKG-INFO
kkkit.egg-info/SOURCES.txt
kkkit.egg-info/dependency_links.txt
kkkit.egg-info/top_level.txt
wu/__init__.py
wu/wy.py